rotest_xml/__init__.py
rotest_xml-0.2.1.dist-info/METADATA
rotest_xml-0.2.1.dist-info/WHEEL
rotest_xml-0.2.1.dist-info/entry_points.txt
rotest_xml-0.2.1.dist-info/top_level.txt
rotest_xml-0.2.1.dist-info/RECORD
